{
  "lastStartNumber": 290176,
  "downloadedChapters": {
    "Unknown Series_61": {
      "timestamp": "2025-04-25T11:20:52.587376",
      "imageCount": 13,
      "githubPath": "series/unknown_series/chapter_61",
      "path": "C:\\Users\\DELL\\Downloads\\asura\\downloads\\unknown_series\\chapter_61"
    },
    "Unknown Series_71": {
      "timestamp": "2025-04-25T11:29:26.706140",
      "imageCount": 10,
      "githubPath": "series/unknown_series/chapter_71",
      "path": "C:\\Users\\DELL\\Downloads\\asura\\downloads\\unknown_series\\chapter_71"
    },
    "Unknown Series_36": {
      "timestamp": "2025-04-25T11:36:16.662672",
      "imageCount": 12,
      "githubPath": "series/unknown_series/chapter_36",
      "path": "C:\\Users\\DELL\\Downloads\\asura\\downloads\\unknown_series\\chapter_36"
    },
    "Unknown Series_28": {
      "timestamp": "2025-04-25T11:42:52.688824",
      "imageCount": 8,
      "githubPath": "series/unknown_series/chapter_28",
      "path": "C:\\Users\\DELL\\Downloads\\asura\\downloads\\unknown_series\\chapter_28"
    },
    "Unknown Series_92": {
      "timestamp": "2025-04-25T11:50:11.918624",
      "imageCount": 12,
      "githubPath": "series/unknown_series/chapter_92",
      "path": "C:\\Users\\DELL\\Downloads\\asura\\downloads\\unknown_series\\chapter_92"
    },
    "Unknown Series_93": {
      "timestamp": "2025-04-25T11:57:42.510216",
      "imageCount": 13,
      "githubPath": "series/unknown_series/chapter_93",
      "path": "C:\\Users\\DELL\\Downloads\\asura\\downloads\\unknown_series\\chapter_93"
    },
    "Unknown Series_94": {
      "timestamp": "2025-04-25T12:04:55.388145",
      "imageCount": 11,
      "githubPath": "series/unknown_series/chapter_94",
      "path": "C:\\Users\\DELL\\Downloads\\asura\\downloads\\unknown_series\\chapter_94"
    },
    "Unknown Series_95": {
      "timestamp": "2025-04-25T12:11:35.074098",
      "imageCount": 10,
      "githubPath": "series/unknown_series/chapter_95",
      "path": "C:\\Users\\DELL\\Downloads\\asura\\downloads\\unknown_series\\chapter_95"
    },
    "Unknown Series_89": {
      "timestamp": "2025-04-25T13:36:03.842304",
      "imageCount": 26,
      "githubPath": "series/unknown_series/chapter_89",
      "path": "C:\\Users\\DELL\\Downloads\\asura\\downloads\\unknown_series\\chapter_89"
    },
    "Unknown Series_unknown": {
      "timestamp": "2025-04-25T13:42:58.814671",
      "imageCount": 8,
      "githubPath": "series/unknown_series/chapter_unknown",
      "path": "C:\\Users\\DELL\\Downloads\\asura\\downloads\\unknown_series\\chapter_unknown"
    },
    "Legend of the Reincarnated Demon_0": {
      "timestamp": "2025-04-25T18:06:20.629949",
      "imageCount": 14,
      "githubPath": "series/legend_of_the_reincarnated_demon/chapter_0",
      "path": "C:\\Users\\DELL\\Downloads\\asura\\downloads\\legend_of_the_reincarnated_demon\\chapter_0"
    },
    "Unknown Series_32": {
      "timestamp": "2025-04-25T18:12:49.712955",
      "imageCount": 10,
      "githubPath": "series/unknown_series/chapter_32",
      "path": "C:\\Users\\DELL\\Downloads\\asura\\downloads\\unknown_series\\chapter_32"
    }
  }
}